pywkpypeteer/__init__.py
pywkpypeteer/pypeteerutils.py
Pywkpypeteer-1.0.2.dist-info/METADATA
Pywkpypeteer-1.0.2.dist-info/WHEEL
Pywkpypeteer-1.0.2.dist-info/top_level.txt
Pywkpypeteer-1.0.2.dist-info/RECORD
