Metadata-Version: 2.1
Name: Pywkpypeteer
Version: 1.0.2
Summary: wangkai python tools
Home-page: http://blog.wangkaicn.cn
Author: wangkai
Author-email: 1719456@qq.com
License: MIT License
Keywords: wangkai python tools
Platform: any
Requires-Dist: pyppeteer
